Metadata-Version: 2.1
Name: openapi3v1
Version: 0.0.2
Summary: Client and Validator of OpenAPI 3 Specifications. Forked from dorthu/openapi3 ad modifications made on top of it
Home-page: https://github.com/anchitarnav/openapi3
Author: Anchit Arnav
License: BSD 3-Clause License
License-File: LICENSE
Requires-Dist: PyYaml
Requires-Dist: requests
Provides-Extra: test
Requires-Dist: pytest ; extra == 'test'
Requires-Dist: pytest-asyncio (==0.16) ; extra == 'test'
Requires-Dist: uvloop ; extra == 'test'
Requires-Dist: hypercorn ; extra == 'test'
Requires-Dist: pydantic ; extra == 'test'
Requires-Dist: fastapi ; extra == 'test'
